[{"WidgetType":"scm","ServiceName":"Palantir.GitLab.RestApiService, Palantir.GitLab","RestApiUrls":["https://gitlab.com/api/v4/projects/<project-number>/merge_requests"],"RestApiHeader":{"AuthorizationToken":"alphanumeric-token","UserAgent":"","ApiVersion":""}},{"WidgetType":"iframe","ServiceName":"<iframe src='iframe-url' style='border: 0'; height='600'; position: 'relative'; width: '80%'; frameborder='0'; scrolling='no'></iframe>","RestApiUrls":null,"RestApiHeader":null},{"WidgetType":"bs","ServiceName":"Palantir.TravisCI.RestApiService, Palantir.TravisCI","RestApiUrls":["https://api.travis-ci.org/repo/<project-number>/builds"],"RestApiHeader":{"AuthorizationToken":"alphanumeric-token","UserAgent":"Mozilla/5.0 (X11; Linux x86_64) AppleWebKit/537.36 (KHTML, like Gecko) Chrome/51.0.2704.106 Safari/537.36 OPR/38.0.2220.41","ApiVersion":"3"}},{"WidgetType":"it","ServiceName":"Palantir.HostedRedmine.RestApiService, Palantir.HostedRedmine","RestApiUrls":["http://www.hostedredmine.com/projects/<project-name>/issues.json?status_id=8&limit=100"],"RestApiHeader":{"AuthorizationToken":"alphanumeric-token","UserAgent":"","ApiVersion":""}}]
